CMakeLists.txt
LICENSE
MANIFEST.in
README.rst
pyproject.toml
setup.cfg
setup.py
src/cpp/export_context.cpp
src/cpp/export_system.cpp
src/cpp/export_tprfile.cpp
src/cpp/gmxpy_exceptions.cpp
src/cpp/gmxpy_exceptions.h
src/cpp/launch_0_2_1.cpp
src/cpp/module.cpp
src/cpp/module.h
src/cpp/mpi_bindings.cpp
src/cpp/mpi_bindings.h
src/cpp/mpi_gromacs_support.cpp
src/cpp/mpi_no_gromacs_support.cpp
src/cpp/pycontext.cpp
src/cpp/pycontext.h
src/cpp/pycontext_create.cpp
src/cpp/pycontext_create_no_mpi.cpp
src/cpp/pysystem.cpp
src/cpp/pysystem.h
src/cpp/wrapped_exceptions.h
src/cpp/wrapped_exceptions_0_1_0.cpp
src/cpp/wrapped_exceptions_0_3_1.cpp
src/gmxapi/__init__.py
src/gmxapi/_logging.py
src/gmxapi/_transform.py
src/gmxapi/abc.py
src/gmxapi/commandline.py
src/gmxapi/datamodel.py
src/gmxapi/exceptions.py
src/gmxapi/gmxconfig.json.in
src/gmxapi/operation.py
src/gmxapi/runtime.py
src/gmxapi/testsupport.py
src/gmxapi/typing.py
src/gmxapi/utility.py
src/gmxapi/version.py
src/gmxapi.egg-info/PKG-INFO
src/gmxapi.egg-info/SOURCES.txt
src/gmxapi.egg-info/dependency_links.txt
src/gmxapi.egg-info/not-zip-safe
src/gmxapi.egg-info/requires.txt
src/gmxapi.egg-info/top_level.txt
src/gmxapi/simulation/__init__.py
src/gmxapi/simulation/abc.py
src/gmxapi/simulation/context.py
src/gmxapi/simulation/fileio.py
src/gmxapi/simulation/mdrun.py
src/gmxapi/simulation/modify_input.py
src/gmxapi/simulation/read_tpr.py
src/gmxapi/simulation/workflow.py
test/CMakeLists.txt
test/conftest.py
test/pytest.ini
test/test_commandline.py
test/test_exceptions.py
test/test_feature_check.py
test/test_fileio.py
test/test_fileio_low_level.py
test/test_mdrun.py
test/test_operation.py
test/test_runtime.py
test/test_subgraph.py
test/testdata.json