Metadata-Version: 2.1
Name: gmxapi
Version: 0.4.2
Summary: gmxapi Python interface for GROMACS.
Home-page: http://gmxapi.org/
Author: GROMACS gmxapi team
Author-email: info@gmxapi.org
License: LGPL
Requires-Python: >=3.7
License-File: LICENSE
